django_ocr/__init__.py
django_ocr/asgi.py
django_ocr/settings.py
django_ocr/urls.py
django_ocr/wsgi.py
ocr/__init__.py
ocr/admin.py
ocr/apps.py
ocr/models.py
ocr/tests.py
ocr/urls.py
ocr/utils.py
ocr/views.py
ocr/migrations/__init__.py
django_ocr-0.0.0.dist-info/LICENSE
django_ocr-0.0.0.dist-info/METADATA
django_ocr-0.0.0.dist-info/WHEEL
django_ocr-0.0.0.dist-info/top_level.txt
django_ocr-0.0.0.dist-info/RECORD
