Metadata-Version: 2.1
Name: django-ocr
Version: 0.0.0
Summary: A lightweight Django-based OCR package
Home-page: https://github.com/fereshtehAhmadi/django-ocr
Author: fereshteh
Author-email: fereshtehahmadi01@gmail.com
Classifier: Programming Language :: Python :: 3
Classifier: Framework :: Django
Classifier: License :: OSI Approved :: MIT License
Requires-Python: >=3.6
License-File: LICENSE
Requires-Dist: django
Requires-Dist: pytesseract
Requires-Dist: Pillow
